py_randomprime/version.py
py_randomprime/rust.abi3.so
py_randomprime/__init__.py
py_randomprime/__main__.py
py_randomprime-16.3.dist-info/top_level.txt
py_randomprime-16.3.dist-info/LICENSE
py_randomprime-16.3.dist-info/RECORD
py_randomprime-16.3.dist-info/WHEEL
py_randomprime-16.3.dist-info/METADATA
